{
    "globalProperties": {
        "Window": {
            "title": "MyEngine",
            "windowWidth": 1024,
            "windowHeight": 576,
            "releaseWindowWidth": 1600,
            "releaseWindowHeight": 900,
            "windowStandardWidth": 1920,
            "windowStandardHeight": 1080,
            "windowDebugWidth": 1920,
            "windowDebugHeight": 1080
        },
        "FPSCounter": {
            "fps": 60.0
        },
        "Keyboard": {
            "enterKey": "Space"
        },
        "JoyPad": {
            "enterPad": "A"
        },
        "SceneManager": {
            "beginScene": "ModelViewer",
            "releaseScene": "Title",
            "removeExclusionTag": [
                "Camera",
                "Light",
                "Shadow"
            ]
        },
        "EngineFunctionManager": {},
        "DebugManager": {},
        "DebugLayer": {},
        "FixedDebugInformation": {
            "scale": [
                0.3125,
                0.3125
            ]
        },
        "Hierarchy": {
            "scale": [
                0.30000001192092898,
                0.30000001192092898
            ],
            "offsetCharCountX": 2,
            "offsetCharCountY": 3,
            "lineSpace": 8.0,
            "nonActiveAlpha": 0.30000001192092898
        },
        "ImGuiInspector": {
            "inspectorPositionX": 1400.0
        },
        "DebugUtility": {},
        "Log": {
            "scale": [
                0.3125,
                0.3125
            ]
        },
        "Pause": {
            "fileName": "System/pause.png",
            "offset": [
                50.0,
                15.0
            ]
        },
        "EngineFuctionChanger": {
            "startRenderPosition": [
                0.0,
                1048.0
            ],
            "spritesFilePath": [
                "System/Game.png",
                "System/MapEditor.png",
                "System/ModelViewer.png"
            ],
            "spriteSpace": 16.0
        },
        "AssetsRenderTextureList": {
            "textureSize": 64,
            "textureDisplayInterval": 32,
            "texturesFilePath": [
                "Assets\\Model\\Player\\U22_player_whiteanime.fbx"
            ]
        },
        "AssetsRenderTextureAdder": {
            "renderPosition": [
                0.0,
                968.0
            ],
            "spriteButtonFilePath": "System/add_mesh.png"
        },
        "ModelViewerLight": {
            "direction": [
                0.923882246017456,
                -8.239712769864127e-7,
                -3.078376664689131e-7,
                -0.38267695903778078
            ],
            "color": [
                1.0,
                0.9999899864196777,
                0.9999899864196777
            ],
            "directionDrawPosition": [
                30.0,
                20.0,
                0.0
            ],
            "lengthDirection": 5.0
        },
        "ShadowMap": {
            "shadowTextureSize": 8192,
            "lightDistance": 290.0,
            "nearClip": 10.0,
            "farClip": 300.0
        },
        "LightManager": {
            "ambientLight": [
                0.0,
                0.0,
                0.0
            ]
        },
        "PointLight": {
            "pointLightMeshFileName": "Shape/Sphere.obj"
        },
        "DrawString": {
            "number": "System/number2.png",
            "font": "System/font2.png"
        }
    }
}